{
	"credit": "Made with Blockbench",
	"texture_size": [128, 128],
	"textures": {
		"0": "gauntlet:decoration/doors/chancery_door"
	},
	"elements": [
		{
			"from": [20.5, -12, 16],
			"to": [23, 32, 18],
			"rotation": {"angle": 0, "axis": "y", "origin": [8, 0, 8]},
			"faces": {
				"north": {"uv": [0, 0, 0.625, 11], "texture": "#0"},
				"east": {"uv": [0, 0, 0, 11], "texture": "#0"},
				"south": {"uv": [6.875, 0, 7.5, 11], "texture": "#0"},
				"west": {"uv": [0.625, 0, 0.125, 11], "texture": "#0"},
				"up": {"uv": [7.5, 0, 0, 0], "texture": "#0"},
				"down": {"uv": [15, 0, 7.5, 0], "texture": "#0"}
			}
		},
		{
			"from": [-7, -12, 16],
			"to": [-4.5, 32, 18],
			"rotation": {"angle": 0, "axis": "y", "origin": [8, 0, 8]},
			"faces": {
				"north": {"uv": [6.875, 0, 7.5, 11], "texture": "#0"},
				"east": {"uv": [7.375, 0, 6.875, 11], "texture": "#0"},
				"south": {"uv": [0, 0, 0.625, 11], "texture": "#0"},
				"west": {"uv": [0, 0, 0, 11], "texture": "#0"},
				"up": {"uv": [0, 0, 7.5, 0], "texture": "#0"},
				"down": {"uv": [7.5, 0, 15, 0], "texture": "#0"}
			}
		},
		{
			"from": [6, -12, 16],
			"to": [10, 26, 18],
			"rotation": {"angle": 0, "axis": "y", "origin": [8, 0, 8]},
			"faces": {
				"north": {"uv": [3.25, 1.5, 4.25, 11], "texture": "#0"},
				"east": {"uv": [7.5, 1.5, 6.875, 11.125], "texture": "#0"},
				"south": {"uv": [3.25, 1.5, 4.25, 11], "texture": "#0"},
				"west": {"uv": [0.625, 1.5, 0.125, 11.125], "texture": "#0"},
				"up": {"uv": [0, 0, 7.5, 0], "texture": "#0"},
				"down": {"uv": [7.5, 0, 15, 0], "texture": "#0"}
			}
		},
		{
			"from": [-7, -12, 17],
			"to": [23, 32, 17],
			"rotation": {"angle": 0, "axis": "y", "origin": [8, 0, 8]},
			"faces": {
				"north": {"uv": [0, 0, 7.5, 11], "texture": "#0"},
				"east": {"uv": [0, 0, 0, 11], "texture": "#0"},
				"south": {"uv": [0, 0, 7.5, 11], "texture": "#0"},
				"west": {"uv": [7.5, 0, 7.5, 11], "texture": "#0"},
				"up": {"uv": [7.5, 0, 0, 0], "texture": "#0"},
				"down": {"uv": [15, 0, 7.5, 0], "texture": "#0"}
			}
		},
		{
			"from": [-4.5, 26, 16],
			"to": [20.5, 32, 18],
			"rotation": {"angle": 0, "axis": "y", "origin": [8, 0, 8]},
			"faces": {
				"north": {"uv": [0.625, 0, 6.875, 1.5], "texture": "#0"},
				"east": {"uv": [0, 0, 0, 11], "texture": "#0"},
				"south": {"uv": [0.625, 0, 6.875, 1.5], "texture": "#0"},
				"west": {"uv": [7.5, 0, 7.5, 11], "texture": "#0"},
				"up": {"uv": [7.5, 0, 0, 0], "texture": "#0"},
				"down": {"uv": [0.625, 1, 6.875, 1.5], "texture": "#0"}
			}
		},
		{
			"from": [-4.5, -12, 16],
			"to": [6, -8.5, 18],
			"faces": {
				"north": {"uv": [4.25, 10.125, 6.875, 11], "texture": "#0"},
				"south": {"uv": [4.25, 10.125, 6.875, 11], "texture": "#0"},
				"up": {"uv": [4.25, 10.125, 6.875, 10.625], "texture": "#0"}
			}
		},
		{
			"from": [10, -12, 16],
			"to": [20.5, -8.5, 18],
			"faces": {
				"north": {"uv": [0.625, 10.125, 3.25, 11], "texture": "#0"},
				"south": {"uv": [0.625, 10.125, 3.25, 11], "texture": "#0"},
				"up": {"uv": [0.625, 10.125, 3.25, 10.625], "texture": "#0"}
			}
		},
		{
			"from": [12.5, -3, 16],
			"to": [13.5, -2, 17],
			"faces": {
				"east": {"uv": [7.625, 0.75, 7.875, 1], "texture": "#0"},
				"west": {"uv": [10, 0.75, 10.25, 1], "texture": "#0"},
				"up": {"uv": [9.625, 0.375, 9.375, 0.125], "texture": "#0"},
				"down": {"uv": [9.625, 1.625, 9.375, 1.375], "texture": "#0"}
			}
		},
		{
			"from": [17, -3, 16],
			"to": [18, -2, 17],
			"faces": {
				"east": {"uv": [7.625, 0.75, 7.875, 1], "texture": "#0"},
				"west": {"uv": [10, 0.75, 10.25, 1], "texture": "#0"},
				"up": {"uv": [8.5, 0.375, 8.25, 0.125], "texture": "#0"},
				"down": {"uv": [8.5, 1.625, 8.25, 1.375], "texture": "#0"}
			}
		},
		{
			"from": [12.5, -3, 15],
			"to": [18, -2, 16],
			"faces": {
				"north": {"uv": [8.25, 0.75, 9.625, 1], "texture": "#0"},
				"east": {"uv": [7.875, 0.75, 8.125, 1], "texture": "#0"},
				"south": {"uv": [8.25, 1.125, 9.625, 1.375], "texture": "#0"},
				"west": {"uv": [9.75, 0.75, 10, 1], "texture": "#0"},
				"up": {"uv": [8.25, 0.625, 9.625, 0.375], "texture": "#0"},
				"down": {"uv": [9.625, 1.375, 8.25, 1.125], "texture": "#0"}
			}
		},
		{
			"from": [-2, -3, 15],
			"to": [3.5, -2, 16],
			"faces": {
				"north": {"uv": [8.25, 0.75, 9.625, 1], "texture": "#0"},
				"east": {"uv": [7.875, 0.75, 8.125, 1], "texture": "#0"},
				"south": {"uv": [8.25, 1.125, 9.625, 1.375], "texture": "#0"},
				"west": {"uv": [9.75, 0.75, 10, 1], "texture": "#0"},
				"up": {"uv": [8.25, 0.625, 9.625, 0.375], "texture": "#0"},
				"down": {"uv": [8.25, 1.375, 9.625, 1.125], "texture": "#0"}
			}
		},
		{
			"from": [2.5, -3, 16],
			"to": [3.5, -2, 17],
			"faces": {
				"east": {"uv": [7.625, 0.75, 7.875, 1], "texture": "#0"},
				"west": {"uv": [10, 0.75, 10.25, 1], "texture": "#0"},
				"up": {"uv": [8.5, 0.375, 8.25, 0.125], "texture": "#0"},
				"down": {"uv": [8.5, 1.625, 8.25, 1.375], "texture": "#0"}
			}
		},
		{
			"from": [-2, -3, 16],
			"to": [-1, -2, 17],
			"faces": {
				"east": {"uv": [7.625, 0.75, 7.875, 1], "texture": "#0"},
				"west": {"uv": [10, 0.75, 10.25, 1], "texture": "#0"},
				"up": {"uv": [9.625, 0.375, 9.375, 0.125], "texture": "#0"},
				"down": {"uv": [9.625, 1.625, 9.375, 1.375], "texture": "#0"}
			}
		}
	],
	"display": {
		"thirdperson_righthand": {
			"rotation": [75, 45, 0],
			"translation": [0, 2.5, 0],
			"scale": [0.375, 0.375, 0.375]
		},
		"thirdperson_lefthand": {
			"rotation": [75, 45, 0],
			"translation": [0, 2.5, 0],
			"scale": [0.375, 0.375, 0.375]
		},
		"firstperson_righthand": {
			"rotation": [0, 45, 0],
			"scale": [0.4, 0.4, 0.4]
		},
		"firstperson_lefthand": {
			"rotation": [0, 225, 0],
			"scale": [0.4, 0.4, 0.4]
		},
		"ground": {
			"translation": [0, 3, 0],
			"scale": [0.25, 0.25, 0.25]
		},
		"gui": {
			"translation": [0, -2, 0],
			"scale": [0.3, 0.3, 0.3]
		},
		"head": {
			"rotation": [0, 180, 0],
			"translation": [0, 13, 7]
		},
		"fixed": {
			"scale": [0.5, 0.5, 0.5]
		}
	}
}